[{"domUser":"m102703440@rafael.turtle.com","telephone":"0515932082","clearance":3,"firstName":"Jean","lastName":"Kunde","mail":"לא ידוע","tz":"949089445","personalNumber":"","rank":"champion","rld":"לא ידוע","job":"Legacy Data Analyst","profession":"Associate","department":"city1","stype":"","hr":null,"company":"bladerunners","isPortalUser":true,"tags":[{"name":"information"}],"domains":["local"]},{"domUser":"l154661040@rafael.turtle.com","telephone":"0592553725","clearance":4,"firstName":"Marina","lastName":"Ortiz","mail":null,"tz":null,"personalNumber":"לא ידוע","rank":"champion","rld":"","job":"Regional Implementation Technician","profession":"Designer","department":"city4","stype":"","hr":null,"company":"","isPortalUser":false,"tags":[{"name":"transportable"}],"domains":["external","local"]},{"domUser":"j504562936@turtle.com","telephone":"0587567314","clearance":1,"firstName":"Nils","lastName":"Kunze","mail":"לא ידוע","tz":"802659425","personalNumber":"539575761","rank":"ultimate","rld":"2021-06-28T05:08:07.848Z","job":"International Communications Administrator","profession":"לא ידוע","department":"city3","stype":"","hr":"","company":"interstellar","isPortalUser":true,"tags":[{"name":"information"}],"domains":["local"]},{"domUser":"e68332700@turtle.com","telephone":"0582553382","clearance":1,"firstName":"Matilda","lastName":"Hirthe","mail":null,"tz":"","personalNumber":null,"rank":"champion","rld":"","job":"Customer Group Associate","profession":"Engineer","department":"city5","stype":"","hr":"Matilda Hirthe","company":"","isPortalUser":true,"tags":[{"name":"transportable"}],"domains":["local"]},{"domUser":"e773651994@donatelo.turtle.com","telephone":"0528611001","clearance":3,"firstName":"Raphael","lastName":"Bergstrom","mail":null,"tz":null,"personalNumber":"316416428","rank":"unknown","rld":null,"job":"Chief Integration Liaison","profession":"null","department":"city2","stype":"","hr":"Raphael Bergstrom","company":"interstellar","isPortalUser":true,"tags":[{"name":"information"},{"name":"information"}],"domains":["local"]},{"domUser":"e739370547@donatelo.turtle.com","telephone":"0557867288","clearance":3,"firstName":"Sylvester","lastName":"Little","mail":"","tz":"","personalNumber":null,"rank":"unknown","rld":null,"job":"Direct Creative Designer","profession":"Director","department":"city4","stype":"","hr":"quis/voluptatem/perferendis/libero","company":"bladerunners","isPortalUser":false,"tags":[{"name":"information"}],"domains":["local","external"]},{"domUser":"m381240769@rafael.turtle.com","telephone":"0522806623","clearance":3,"firstName":"Raegan","lastName":"Abshire","mail":"","tz":null,"personalNumber":"","rank":"unknown","rld":"לא ידוע","job":"Principal Factors Technician","profession":"Facilitator","department":"city4","stype":"","hr":"accusamus/ipsam/ut/qui","company":"odyssey","isPortalUser":true,"tags":[],"domains":["external"]},{"domUser":"e44206617@rafael.turtle.com","telephone":"0562109895","clearance":2,"firstName":"Akeem","lastName":"Marquardt","mail":"לא ידוע","tz":"167177666","personalNumber":null,"rank":"unknown","rld":"","job":"Dynamic Applications Technician","profession":"Engineer","department":"city5","stype":"","hr":null,"company":"odyssey","isPortalUser":true,"tags":[{"name":"information"}],"domains":["local"]},{"domUser":"j919252595@turtle.com","telephone":"0561165274","clearance":2,"firstName":"Ernestina","lastName":"Gulgowski","mail":"","tz":"232549667","personalNumber":null,"rank":"unknown","rld":null,"job":"Global Factors Officer","profession":"Producer","department":"city6","stype":"","hr":"","company":"bladerunners","isPortalUser":true,"tags":[{"name":"information"},{"name":"transportable"}],"domains":["external","local"]},{"domUser":"l407064485@turtle.com","telephone":"0534553720","clearance":5,"firstName":"Luther","lastName":"Strosin","mail":"לא ידוע","tz":"","personalNumber":null,"rank":"mega","rld":"לא ידוע","job":"Lead Data Engineer","profession":"Officer","department":"city1","stype":"","hr":"et/nihil/consequatur/fugit","company":"","isPortalUser":false,"tags":[],"domains":["local","external"]},{"domUser":"g573184563@turtle.com","telephone":"0511849343","clearance":3,"firstName":"Gust","lastName":"Torp","mail":"לא ידוע","tz":"","personalNumber":"504368908","rank":"unknown","rld":"","job":"Legacy Security Supervisor","profession":"לא ידוע","department":"city3","stype":"","hr":null,"company":"odyssey","isPortalUser":true,"tags":[{"name":"transportable"}],"domains":["local"]},{"domUser":"g185091873@donatelo.turtle.com","telephone":"0544600407","clearance":5,"firstName":"Mckayla","lastName":"Ferry","mail":"","tz":"","personalNumber":"","rank":"mega","rld":null,"job":"Central Data Specialist","profession":"Supervisor","department":"city6","stype":"","hr":null,"company":"interstellar","isPortalUser":false,"tags":[{"name":"information"},{"name":"transportable"}],"domains":["external","local"]},{"domUser":"m949494714@donatelo.turtle.com","telephone":"0554365528","clearance":3,"firstName":"Derick","lastName":"Boehm","mail":null,"tz":"924703937","personalNumber":"125813638","rank":"unknown","rld":"לא ידוע","job":"Central Communications Executive","profession":"null","department":"city5","stype":"","hr":"aspernatur/et/earum/possimus","company":"bladerunners","isPortalUser":false,"tags":[],"domains":["local","external"]},{"domUser":"e554873055@turtle.com","telephone":"0502028365","clearance":5,"firstName":"Lydia","lastName":"Roberts","mail":"","tz":"","personalNumber":null,"rank":"ultimate","rld":"","job":"International Brand Planner","profession":"","department":"city3","stype":"","hr":"","company":"","isPortalUser":false,"tags":[{"name":"information"}],"domains":["local"]},{"domUser":"e699597293@turtle.com","telephone":"0528352317","clearance":5,"firstName":"Reginald","lastName":"Skiles","mail":"Gussie.Thompson@turtleS.com","tz":null,"personalNumber":null,"rank":"champion","rld":"","job":"National Accountability Associate","profession":"לא ידוע","department":"city5","stype":"","hr":"voluptatem/blanditiis/modi/sed","company":"armagadon","isPortalUser":false,"tags":[{"name":"transportable"}],"domains":["local"]},{"domUser":"e159137748@turtle.com","telephone":"0541386324","clearance":2,"firstName":"Carmella","lastName":"Marks","mail":"","tz":"","personalNumber":"","rank":"mega","rld":"","job":"Central Accountability Consultant","profession":"Developer","department":"city6","stype":"","hr":"","company":"interstellar","isPortalUser":false,"tags":[],"domains":["local","external"]},{"domUser":"e109597853@turtle.com","telephone":"0555072593","clearance":4,"firstName":"Gabrielle","lastName":"Gleichner","mail":"לא ידוע","tz":"","personalNumber":"842002534","rank":"ultimate","rld":"לא ידוע","job":"Customer Web Planner","profession":"","department":"city1","stype":"","hr":"Gabrielle Gleichner","company":"","isPortalUser":false,"tags":[{"name":"transportable"}],"domains":["external","local"]},{"domUser":"m775454450@turtle.com","telephone":"0574062494","clearance":4,"firstName":"Mohammad","lastName":"MacGyver","mail":"Bobby.Zemlak97@turtleS.com","tz":"לא ידוע","personalNumber":"","rank":"rookie","rld":"לא ידוע","job":"Internal Mobility Designer","profession":"Specialist","department":"city6","stype":"","hr":null,"company":null,"isPortalUser":true,"tags":[{"name":"transportable"},{"name":"transportable"}],"domains":["local","external"]},{"domUser":"m907430986@turtle.com","telephone":"0551084001","clearance":2,"firstName":"Dedrick","lastName":"Ledner","mail":null,"tz":null,"personalNumber":"767836450","rank":"unknown","rld":"2016-07-17T01:02:18.308Z","job":"Human Interactions Strategist","profession":"לא ידוע","department":"city3","stype":"","hr":"quis/at/tempore/aliquid","company":"interstellar","isPortalUser":false,"tags":[{"name":"transportable"}],"domains":["local","external"]},{"domUser":"m103049668@turtle.com","telephone":"0594260354","clearance":2,"firstName":"Bernie","lastName":"Marks","mail":"לא ידוע","tz":"333379402","personalNumber":"לא ידוע","rank":"ultimate","rld":"","job":"Dynamic Creative Analyst","profession":"לא ידוע","department":"city4","stype":"","hr":"Bernie Marks","company":"","isPortalUser":true,"tags":[],"domains":["external"]},{"domUser":"e965797217@rafael.turtle.com","telephone":"0585684797","clearance":3,"firstName":"Christop","lastName":"Johns","mail":"","tz":"","personalNumber":"לא ידוע","rank":"unknown","rld":"2014-10-25T02:13:50.068Z","job":"Legacy Identity Engineer","profession":"null","department":"city1","stype":"","hr":"Christop Johns","company":"bladerunners","isPortalUser":false,"tags":[{"name":"transportable"},{"name":"transportable"}],"domains":["external","local"]},{"domUser":"e379773740@turtle.com","telephone":"0589655595","clearance":5,"firstName":"Claire","lastName":"O'Reilly","mail":"","tz":"","personalNumber":"לא ידוע","rank":"mega","rld":null,"job":"Future Operations Consultant","profession":"לא ידוע","department":"city3","stype":"","hr":"ut/quia/inventore/earum","company":"interstellar","isPortalUser":true,"tags":[{"name":"information"},{"name":"transportable"}],"domains":["local","external"]},{"domUser":"i671750827@turtle.com","telephone":"0564293954","clearance":4,"firstName":"Ernie","lastName":"McGlynn","mail":"","tz":"","personalNumber":null,"rank":"rookie","rld":"לא ידוע","job":"Regional Program Facilitator","profession":"לא ידוע","department":"city2","stype":"","hr":null,"company":"","isPortalUser":true,"tags":[{"name":"transportable"}],"domains":["local"]},{"domUser":"g864000676@turtle.com","telephone":"0574356653","clearance":4,"firstName":"Elwin","lastName":"Breitenberg","mail":"Guy_Nicolas53@turtleS.com","tz":"","personalNumber":"33506628","rank":"champion","rld":"לא ידוע","job":"Internal Web Designer","profession":"Specialist","department":"city1","stype":"","hr":null,"company":"armagadon","isPortalUser":true,"tags":[{"name":"information"}],"domains":["local","external"]},{"domUser":"e110919437@turtle.com","telephone":"0565149659","clearance":5,"firstName":"Max","lastName":"Moore","mail":"","tz":"","personalNumber":"163613751","rank":"unknown","rld":null,"job":"Legacy Group Orchestrator","profession":"null","department":"city4","stype":"","hr":"Max Moore","company":null,"isPortalUser":false,"tags":[{"name":"transportable"}],"domains":["local"]},{"domUser":"j758341123@rafael.turtle.com","telephone":"0597968484","clearance":1,"firstName":"Domenica","lastName":"Legros","mail":"לא ידוע","tz":"","personalNumber":null,"rank":"rookie","rld":null,"job":"Future Program Administrator","profession":"Analyst","department":"city4","stype":"","hr":"","company":"odyssey","isPortalUser":true,"tags":[{"name":"information"}],"domains":["external"]},{"domUser":"e880199515@turtle.com","telephone":"0568416908","clearance":1,"firstName":"Alvah","lastName":"Toy","mail":"לא ידוע","tz":null,"personalNumber":"","rank":"ultimate","rld":"לא ידוע","job":"Central Assurance Representative","profession":"Consultant","department":"city6","stype":"","hr":"saepe/nihil/et/quas","company":"armagadon","isPortalUser":false,"tags":[{"name":"information"}],"domains":["external"]},{"domUser":"m487342146@turtle.com","telephone":"0596181968","clearance":3,"firstName":"Blake","lastName":"Frami","mail":"לא ידוע","tz":"","personalNumber":"לא ידוע","rank":"unknown","rld":"לא ידוע","job":"Corporate Research Executive","profession":"","department":"city1","stype":"","hr":"Blake Frami","company":"odyssey","isPortalUser":false,"tags":[],"domains":["external","local"]},{"domUser":"e98825028@turtle.com","telephone":"0532626624","clearance":5,"firstName":"Elijah","lastName":"Zboncak","mail":"Quinten_Jerde77@turtleS.com","tz":"993387562","personalNumber":null,"rank":"ultimate","rld":"2013-12-19T23:02:58.714Z","job":"Global Infrastructure Orchestrator","profession":"","department":"city2","stype":"","hr":"","company":"interstellar","isPortalUser":true,"tags":[{"name":"transportable"}],"domains":["external","local"]},{"domUser":"m596439011@turtle.com","telephone":"0514954503","clearance":2,"firstName":"Charles","lastName":"Wisozk","mail":"לא ידוע","tz":null,"personalNumber":"154117660","rank":"unknown","rld":"לא ידוע","job":"Legacy Creative Designer","profession":"Consultant","department":"city1","stype":"","hr":null,"company":"bladerunners","isPortalUser":false,"tags":[],"domains":["local"]},{"domUser":"e23663676@rafael.turtle.com","telephone":"0589024693","clearance":1,"firstName":"Enos","lastName":"Ziemann","mail":"","tz":"לא ידוע","personalNumber":null,"rank":"rookie","rld":"לא ידוע","job":"International Functionality Director","profession":"לא ידוע","department":"city3","stype":"","hr":"","company":"interstellar","isPortalUser":false,"tags":[{"name":"transportable"}],"domains":["local","external"]},{"domUser":"e475337793@turtle.com","telephone":"0571079064","clearance":3,"firstName":"Alec","lastName":"Howe","mail":"לא ידוע","tz":"370512014","personalNumber":"","rank":"champion","rld":"לא ידוע","job":"Direct Paradigm Architect","profession":"null","department":"city6","stype":"","hr":"Alec Howe","company":"bladerunners","isPortalUser":false,"tags":[{"name":"transportable"},{"name":"information"}],"domains":["local"]},{"domUser":"j477042349@turtle.com","telephone":"0595386253","clearance":1,"firstName":"Edwina","lastName":"Gerhold","mail":"","tz":"לא ידוע","personalNumber":null,"rank":"champion","rld":null,"job":"Central Web Coordinator","profession":"Orchestrator","department":"city1","stype":"","hr":"","company":"bladerunners","isPortalUser":true,"tags":[],"domains":["local"]},{"domUser":"e96947017@turtle.com","telephone":"0557374436","clearance":5,"firstName":"Leda","lastName":"Hoeger","mail":null,"tz":"לא ידוע","personalNumber":"982829148","rank":"ultimate","rld":null,"job":"Global Web Analyst","profession":"Associate","department":"city4","stype":"","hr":"perspiciatis/necessitatibus/reiciendis/sit","company":"","isPortalUser":true,"tags":[],"domains":["external"]},{"domUser":"e512693305@turtle.com","telephone":"0519199468","clearance":1,"firstName":"Jaeden","lastName":"Medhurst","mail":"","tz":"לא ידוע","personalNumber":"646930660","rank":"champion","rld":"לא ידוע","job":"Lead Usability Engineer","profession":"Assistant","department":"city1","stype":"","hr":"suscipit/placeat/omnis/et","company":"לא ידוע","isPortalUser":false,"tags":[],"domains":["external","local"]},{"domUser":"l394978417@turtle.com","telephone":"0558219379","clearance":1,"firstName":"Hipolito","lastName":"Keebler","mail":null,"tz":"","personalNumber":"","rank":"mega","rld":null,"job":"Human Infrastructure Consultant","profession":"null","department":"city4","stype":"","hr":null,"company":"לא ידוע","isPortalUser":false,"tags":[{"name":"information"},{"name":"transportable"}],"domains":["external","local"]},{"domUser":"e194814066@donatelo.turtle.com","telephone":"0521090873","clearance":4,"firstName":"Trudie","lastName":"Hettinger","mail":"","tz":"","personalNumber":"לא ידוע","rank":"rookie","rld":"2022-09-05T18:35:07.626Z","job":"National Directives Executive","profession":"null","department":"city1","stype":"","hr":"Trudie Hettinger","company":"interstellar","isPortalUser":true,"tags":[],"domains":["external","local"]},{"domUser":"g699252578@turtle.com","telephone":"0529357094","clearance":5,"firstName":"Adella","lastName":"Marquardt","mail":null,"tz":null,"personalNumber":null,"rank":"champion","rld":"","job":"Corporate Security Planner","profession":"null","department":"city3","stype":"","hr":"","company":"odyssey","isPortalUser":false,"tags":[{"name":"transportable"}],"domains":["external","local"]},{"domUser":"j592914651@rafael.turtle.com","telephone":"0555285921","clearance":2,"firstName":"Lemuel","lastName":"Dach","mail":null,"tz":null,"personalNumber":"לא ידוע","rank":"rookie","rld":"לא ידוע","job":"International Integration Assistant","profession":"Executive","department":"city4","stype":"","hr":"et/aspernatur/fuga/eaque","company":"armagadon","isPortalUser":true,"tags":[],"domains":["external"]},{"domUser":"m123244973@turtle.com","telephone":"0579913630","clearance":2,"firstName":"Solon","lastName":"Doyle","mail":"","tz":null,"personalNumber":"לא ידוע","rank":"ultimate","rld":null,"job":"International Factors Developer","profession":"Agent","department":"city3","stype":"","hr":null,"company":"interstellar","isPortalUser":false,"tags":[{"name":"transportable"}],"domains":["external","local"]},{"domUser":"e18485070@turtle.com","telephone":"0599475898","clearance":3,"firstName":"Jazmin","lastName":"Braun","mail":"Melyna.Grady@turtleS.com","tz":"739543361","personalNumber":"","rank":"champion","rld":"לא ידוע","job":"Lead Group Planner","profession":"","department":"city1","stype":"","hr":"Jazmin Braun","company":null,"isPortalUser":true,"tags":[],"domains":["external","local"]},{"domUser":"g181697967@donatelo.turtle.com","telephone":"0518707219","clearance":3,"firstName":"Jana","lastName":"Hansen","mail":"","tz":"לא ידוע","personalNumber":"","rank":"champion","rld":"לא ידוע","job":"Product Tactics Supervisor","profession":"","department":"city5","stype":"","hr":null,"company":"bladerunners","isPortalUser":true,"tags":[{"name":"information"}],"domains":["external"]},{"domUser":"m545480353@rafael.turtle.com","telephone":"0569511231","clearance":4,"firstName":"Murray","lastName":"Homenick","mail":"לא ידוע","tz":"לא ידוע","personalNumber":"88605291","rank":"unknown","rld":"2016-06-19T05:56:48.217Z","job":"Direct Group Architect","profession":"לא ידוע","department":"city4","stype":"","hr":null,"company":"לא ידוע","isPortalUser":true,"tags":[{"name":"transportable"}],"domains":["external"]},{"domUser":"m622302268@turtle.com","telephone":"0535402180","clearance":2,"firstName":"Rachael","lastName":"Kuhn","mail":"Kody_Ratke45@turtleS.com","tz":"792303745","personalNumber":"","rank":"ultimate","rld":"","job":"Product Data Director","profession":"","department":"city5","stype":"","hr":"quaerat/nihil/natus/et","company":null,"isPortalUser":true,"tags":[{"name":"information"}],"domains":["local","external"]},{"domUser":"m886445047@turtle.com","telephone":"0571767944","clearance":2,"firstName":"Kieran","lastName":"Bogisich","mail":"Maurine58@turtleS.com","tz":"","personalNumber":"","rank":"mega","rld":"","job":"Regional Metrics Consultant","profession":"Strategist","department":"city1","stype":"","hr":"Kieran Bogisich","company":"bladerunners","isPortalUser":true,"tags":[],"domains":["local","external"]},{"domUser":"m724871521@rafael.turtle.com","telephone":"0562267843","clearance":3,"firstName":"Zane","lastName":"Langosh","mail":"לא ידוע","tz":"לא ידוע","personalNumber":"371971590","rank":"rookie","rld":"לא ידוע","job":"Dynamic Accountability Manager","profession":"null","department":"city2","stype":"","hr":"Zane Langosh","company":"","isPortalUser":true,"tags":[],"domains":["external","local"]},{"domUser":"e859505826@turtle.com","telephone":"0564828676","clearance":3,"firstName":"Dasia","lastName":"Tillman","mail":"לא ידוע","tz":"270820574","personalNumber":"לא ידוע","rank":"ultimate","rld":null,"job":"Forward Mobility Consultant","profession":"","department":"city1","stype":"","hr":"Dasia Tillman","company":"odyssey","isPortalUser":true,"tags":[],"domains":["external","local"]},{"domUser":"e430677770@donatelo.turtle.com","telephone":"0597726307","clearance":3,"firstName":"Mariano","lastName":"Raynor","mail":"לא ידוע","tz":null,"personalNumber":"לא ידוע","rank":"rookie","rld":"לא ידוע","job":"Internal Intranet Coordinator","profession":"Planner","department":"city2","stype":"","hr":"officiis/unde/vel/repellat","company":"interstellar","isPortalUser":false,"tags":[{"name":"transportable"},{"name":"transportable"}],"domains":["external","local"]},{"domUser":"e454096742@turtle.com","telephone":"0583441214","clearance":5,"firstName":"Jordi","lastName":"Fritsch","mail":"לא ידוע","tz":"854448099","personalNumber":"","rank":"mega","rld":"לא ידוע","job":"Product Marketing Representative","profession":"Officer","department":"city2","stype":"","hr":"ipsa/quasi/voluptatibus/adipisci","company":"bladerunners","isPortalUser":true,"tags":[{"name":"transportable"}],"domains":["local"]},{"domUser":"g345266472@donatelo.turtle.com","telephone":"0512109435","clearance":4,"firstName":"Elmira","lastName":"Heathcote","mail":null,"tz":null,"personalNumber":"917424040","rank":"champion","rld":null,"job":"Principal Branding Engineer","profession":"Consultant","department":"city1","stype":"","hr":"nihil/ut/non/quis","company":"","isPortalUser":true,"tags":[{"name":"transportable"}],"domains":["external","local"]},{"domUser":"l886832136@rafael.turtle.com","telephone":"0581823618","clearance":2,"firstName":"Rosamond","lastName":"Reynolds","mail":"לא ידוע","tz":"735541518","personalNumber":null,"rank":"mega","rld":null,"job":"Dynamic Markets Designer","profession":"Producer","department":"city5","stype":"","hr":"Rosamond Reynolds","company":"bladerunners","isPortalUser":false,"tags":[{"name":"information"}],"domains":["external","local"]},{"domUser":"m530578963@turtle.com","telephone":"0581569036","clearance":3,"firstName":"Ford","lastName":"Green","mail":"Jaclyn.Kuvalis27@turtleS.com","tz":"670406339","personalNumber":"980343158","rank":"champion","rld":"לא ידוע","job":"Global Quality Liaison","profession":"null","department":"city6","stype":"","hr":"","company":"armagadon","isPortalUser":false,"tags":[{"name":"transportable"}],"domains":["local"]},{"domUser":"m618948485@turtle.com","telephone":"0509666095","clearance":2,"firstName":"Rachelle","lastName":"McCullough","mail":null,"tz":"לא ידוע","personalNumber":"","rank":"unknown","rld":"לא ידוע","job":"Product Solutions Representative","profession":"","department":"city5","stype":"","hr":"dolorem/ut/et/et","company":null,"isPortalUser":false,"tags":[{"name":"information"},{"name":"information"}],"domains":["local"]},{"domUser":"e412237075@turtle.com","telephone":"0536400133","clearance":2,"firstName":"Jeanne","lastName":"White","mail":null,"tz":null,"personalNumber":"לא ידוע","rank":"champion","rld":"לא ידוע","job":"Internal Assurance Producer","profession":"Orchestrator","department":"city1","stype":"","hr":"","company":"interstellar","isPortalUser":false,"tags":[{"name":"information"}],"domains":["local","external"]},{"domUser":"m318996116@donatelo.turtle.com","telephone":"0537897053","clearance":1,"firstName":"Kody","lastName":"Ward","mail":null,"tz":null,"personalNumber":"לא ידוע","rank":"ultimate","rld":"לא ידוע","job":"Internal Data Technician","profession":"Agent","department":"city3","stype":"","hr":null,"company":"odyssey","isPortalUser":true,"tags":[],"domains":["external","local"]},{"domUser":"e600894490@rafael.turtle.com","telephone":"0524840651","clearance":2,"firstName":"King","lastName":"Bergnaum","mail":"לא ידוע","tz":"365893668","personalNumber":"909997728","rank":"champion","rld":null,"job":"Customer Assurance Coordinator","profession":"לא ידוע","department":"city2","stype":"","hr":null,"company":"interstellar","isPortalUser":false,"tags":[{"name":"information"}],"domains":["external"]},{"domUser":"e722416832@turtle.com","telephone":"0524456181","clearance":2,"firstName":"Chaz","lastName":"Mitchell","mail":"","tz":null,"personalNumber":"17166301","rank":"champion","rld":"2027-09-29T18:42:16.475Z","job":"Chief Metrics Agent","profession":"null","department":"city3","stype":"","hr":"Chaz Mitchell","company":"interstellar","isPortalUser":false,"tags":[{"name":"transportable"},{"name":"transportable"}],"domains":["external","local"]},{"domUser":"e223076445@rafael.turtle.com","telephone":"0586716518","clearance":4,"firstName":"Carmen","lastName":"Schulist","mail":null,"tz":"לא ידוע","personalNumber":"234595857","rank":"mega","rld":null,"job":"Corporate Infrastructure Coordinator","profession":"Liaison","department":"city1","stype":"","hr":"","company":"bladerunners","isPortalUser":false,"tags":[{"name":"information"},{"name":"information"}],"domains":["local","external"]},{"domUser":"e243847926@turtle.com","telephone":"0542268029","clearance":5,"firstName":"Tara","lastName":"Beier","mail":"לא ידוע","tz":"","personalNumber":"960198731","rank":"rookie","rld":null,"job":"Customer Response Strategist","profession":"null","department":"city4","stype":"","hr":null,"company":null,"isPortalUser":true,"tags":[{"name":"information"}],"domains":["local","external"]},{"domUser":"j274159645@turtle.com","telephone":"0592118551","clearance":2,"firstName":"Reece","lastName":"Zieme","mail":"Sally_Halvorson32@turtleS.com","tz":"לא ידוע","personalNumber":"570742301","rank":"ultimate","rld":"לא ידוע","job":"Chief Identity Orchestrator","profession":"לא ידוע","department":"city4","stype":"","hr":"Reece Zieme","company":"","isPortalUser":false,"tags":[],"domains":["local","external"]},{"domUser":"e861247865@turtle.com","telephone":"0524561891","clearance":5,"firstName":"Nadia","lastName":"Kunze","mail":null,"tz":"","personalNumber":"","rank":"champion","rld":"","job":"Chief Group Liaison","profession":"לא ידוע","department":"city5","stype":"","hr":"Nadia Kunze","company":"לא ידוע","isPortalUser":false,"tags":[],"domains":["local"]},{"domUser":"e23163009@turtle.com","telephone":"0522121234","clearance":2,"firstName":"Jerrell","lastName":"McCullough","mail":"לא ידוע","tz":null,"personalNumber":"לא ידוע","rank":"champion","rld":"2022-08-29T22:16:38.111Z","job":"Senior Mobility Supervisor","profession":"Manager","department":"city4","stype":"","hr":"Jerrell McCullough","company":"bladerunners","isPortalUser":true,"tags":[],"domains":["external"]},{"domUser":"e550953931@turtle.com","telephone":"0509355176","clearance":2,"firstName":"Cortney","lastName":"Friesen","mail":"Ramiro_Hackett@turtleS.com","tz":"392358305","personalNumber":"","rank":"mega","rld":null,"job":"Product Metrics Consultant","profession":"Liaison","department":"city1","stype":"","hr":"et/voluptas/enim/odio","company":"interstellar","isPortalUser":false,"tags":[{"name":"information"}],"domains":["local"]},{"domUser":"e180295868@donatelo.turtle.com","telephone":"0569671781","clearance":1,"firstName":"Teresa","lastName":"Simonis","mail":null,"tz":"","personalNumber":"לא ידוע","rank":"mega","rld":"לא ידוע","job":"Principal Security Agent","profession":"","department":"city6","stype":"","hr":null,"company":"interstellar","isPortalUser":false,"tags":[{"name":"transportable"},{"name":"information"}],"domains":["local"]},{"domUser":"j364507742@turtle.com","telephone":"0586999435","clearance":4,"firstName":"Deron","lastName":"Cartwright","mail":null,"tz":"339763799","personalNumber":"לא ידוע","rank":"mega","rld":"","job":"Dynamic Applications Coordinator","profession":"null","department":"city3","stype":"","hr":"Deron Cartwright","company":"armagadon","isPortalUser":true,"tags":[{"name":"information"},{"name":"transportable"}],"domains":["local"]},{"domUser":"e749033033@turtle.com","telephone":"0571651791","clearance":3,"firstName":"Mabel","lastName":"Kemmer","mail":"","tz":"","personalNumber":"","rank":"mega","rld":"לא ידוע","job":"Chief Web Executive","profession":"Planner","department":"city5","stype":"","hr":"","company":"odyssey","isPortalUser":false,"tags":[{"name":"transportable"}],"domains":["local","external"]},{"domUser":"e7047170@donatelo.turtle.com","telephone":"0571948048","clearance":2,"firstName":"Alvena","lastName":"Donnelly","mail":"לא ידוע","tz":"לא ידוע","personalNumber":"","rank":"unknown","rld":"2021-05-03T21:27:20.914Z","job":"Global Communications Producer","profession":"לא ידוע","department":"city1","stype":"","hr":"","company":"לא ידוע","isPortalUser":false,"tags":[],"domains":["local"]},{"domUser":"l444523843@turtle.com","telephone":"0579692612","clearance":2,"firstName":"Ibrahim","lastName":"Vandervort","mail":"Kiera51@turtleS.com","tz":"לא ידוע","personalNumber":"","rank":"champion","rld":null,"job":"Investor Configuration Producer","profession":"null","department":"city5","stype":"","hr":"Ibrahim Vandervort","company":null,"isPortalUser":false,"tags":[{"name":"information"}],"domains":["local","external"]},{"domUser":"e567564501@turtle.com","telephone":"0519987553","clearance":2,"firstName":"Quinn","lastName":"Fisher","mail":"","tz":null,"personalNumber":"לא ידוע","rank":"mega","rld":"","job":"Product Brand Director","profession":"null","department":"city6","stype":"","hr":"voluptates/et/est/cum","company":"odyssey","isPortalUser":true,"tags":[{"name":"information"}],"domains":["external"]},{"domUser":"m526673180@turtle.com","telephone":"0547903407","clearance":1,"firstName":"Terrell","lastName":"Ullrich","mail":"","tz":null,"personalNumber":"357908847","rank":"champion","rld":"","job":"Product Implementation Liaison","profession":"Director","department":"city3","stype":"","hr":null,"company":"armagadon","isPortalUser":true,"tags":[{"name":"transportable"}],"domains":["local"]},{"domUser":"g539501954@turtle.com","telephone":"0595974266","clearance":1,"firstName":"Marc","lastName":"Schuster","mail":"Demetris.Dooley@turtleS.com","tz":"973376767","personalNumber":"לא ידוע","rank":"unknown","rld":"2024-12-08T01:39:56.850Z","job":"Product Quality Associate","profession":"לא ידוע","department":"city3","stype":"","hr":null,"company":"armagadon","isPortalUser":false,"tags":[{"name":"transportable"},{"name":"transportable"}],"domains":["local"]},{"domUser":"e338520449@rafael.turtle.com","telephone":"0509727734","clearance":1,"firstName":"Jarred","lastName":"Olson","mail":null,"tz":"","personalNumber":"50744221","rank":"unknown","rld":"לא ידוע","job":"Chief Metrics Administrator","profession":"Assistant","department":"city4","stype":"","hr":"Jarred Olson","company":"odyssey","isPortalUser":false,"tags":[],"domains":["external"]},{"domUser":"g241425489@turtle.com","telephone":"0536947695","clearance":1,"firstName":"Anais","lastName":"Keebler","mail":"Guy.Effertz@turtleS.com","tz":"לא ידוע","personalNumber":"","rank":"ultimate","rld":"לא ידוע","job":"Future Quality Officer","profession":"","department":"city3","stype":"","hr":"","company":"interstellar","isPortalUser":false,"tags":[{"name":"information"},{"name":"information"}],"domains":["local"]},{"domUser":"m737649086@turtle.com","telephone":"0571875602","clearance":4,"firstName":"Torey","lastName":"Cruickshank","mail":"Favian99@turtleS.com","tz":"","personalNumber":null,"rank":"rookie","rld":"","job":"Direct Security Manager","profession":"לא ידוע","department":"city6","stype":"","hr":"Torey Cruickshank","company":"","isPortalUser":true,"tags":[{"name":"transportable"}],"domains":["external"]},{"domUser":"l577687304@turtle.com","telephone":"0537557297","clearance":5,"firstName":"Lori","lastName":"Reinger","mail":"לא ידוע","tz":"לא ידוע","personalNumber":"","rank":"rookie","rld":"2020-09-14T09:36:43.532Z","job":"Corporate Marketing Designer","profession":"Officer","department":"city4","stype":"","hr":"","company":"","isPortalUser":false,"tags":[{"name":"transportable"},{"name":"transportable"}],"domains":["external","local"]},{"domUser":"e828072587@turtle.com","telephone":"0522951844","clearance":4,"firstName":"Mohammed","lastName":"Heaney","mail":null,"tz":"","personalNumber":"לא ידוע","rank":"champion","rld":"2021-08-23T23:11:41.741Z","job":"Investor Optimization Strategist","profession":"Developer","department":"city3","stype":"","hr":null,"company":"interstellar","isPortalUser":false,"tags":[],"domains":["external"]},{"domUser":"i645613423@turtle.com","telephone":"0567117023","clearance":4,"firstName":"Julian","lastName":"Considine","mail":"","tz":"לא ידוע","personalNumber":null,"rank":"rookie","rld":null,"job":"Regional Data Facilitator","profession":"","department":"city6","stype":"","hr":"vero/sit/rerum/quibusdam","company":"","isPortalUser":false,"tags":[{"name":"information"},{"name":"information"}],"domains":["local","external"]},{"domUser":"e895305547@rafael.turtle.com","telephone":"0501780923","clearance":4,"firstName":"Jeramie","lastName":"O'Keefe","mail":null,"tz":"945815876","personalNumber":"","rank":"champion","rld":"2022-10-28T16:30:28.103Z","job":"Global Directives Agent","profession":"Strategist","department":"city4","stype":"","hr":null,"company":"bladerunners","isPortalUser":true,"tags":[],"domains":["external","local"]},{"domUser":"e777674411@turtle.com","telephone":"0516684922","clearance":2,"firstName":"Jamal","lastName":"Ebert","mail":"לא ידוע","tz":null,"personalNumber":null,"rank":"mega","rld":null,"job":"District Interactions Director","profession":"Officer","department":"city2","stype":"","hr":"","company":"odyssey","isPortalUser":true,"tags":[{"name":"information"}],"domains":["local","external"]},{"domUser":"e366543454@donatelo.turtle.com","telephone":"0525529566","clearance":4,"firstName":"Ross","lastName":"Stracke","mail":null,"tz":"","personalNumber":"824386230","rank":"rookie","rld":"2025-08-08T10:40:17.803Z","job":"Senior Integration Facilitator","profession":"Executive","department":"city5","stype":"","hr":null,"company":"","isPortalUser":false,"tags":[],"domains":["external","local"]},{"domUser":"e33895192@turtle.com","telephone":"0588854299","clearance":5,"firstName":"Leo","lastName":"King","mail":"","tz":"984975714","personalNumber":null,"rank":"unknown","rld":"","job":"Human Security Director","profession":"Officer","department":"city6","stype":"","hr":null,"company":"odyssey","isPortalUser":true,"tags":[{"name":"information"}],"domains":["external","local"]},{"domUser":"g433784142@turtle.com","telephone":"0579527301","clearance":2,"firstName":"Kristy","lastName":"Volkman","mail":"לא ידוע","tz":"815460910","personalNumber":"777846007","rank":"mega","rld":"","job":"Central Program Planner","profession":"Administrator","department":"city1","stype":"","hr":null,"company":null,"isPortalUser":true,"tags":[],"domains":["external"]},{"domUser":"l876592262@turtle.com","telephone":"0567024961","clearance":1,"firstName":"Shayne","lastName":"Stoltenberg","mail":"לא ידוע","tz":null,"personalNumber":"533903357","rank":"rookie","rld":null,"job":"Dynamic Response Agent","profession":"","department":"city5","stype":"","hr":null,"company":"odyssey","isPortalUser":false,"tags":[{"name":"information"}],"domains":["local"]},{"domUser":"m171322669@rafael.turtle.com","telephone":"0566994736","clearance":1,"firstName":"Maddison","lastName":"Will","mail":null,"tz":null,"personalNumber":"לא ידוע","rank":"unknown","rld":"","job":"Principal Assurance Engineer","profession":"null","department":"city2","stype":"","hr":null,"company":"bladerunners","isPortalUser":false,"tags":[],"domains":["local"]},{"domUser":"e617745487@turtle.com","telephone":"0584783696","clearance":3,"firstName":"Tremaine","lastName":"Frami","mail":null,"tz":"","personalNumber":"499265536","rank":"rookie","rld":"2021-06-05T20:13:11.873Z","job":"Human Brand Strategist","profession":"לא ידוע","department":"city6","stype":"","hr":null,"company":null,"isPortalUser":true,"tags":[],"domains":["local","external"]},{"domUser":"g553817021@donatelo.turtle.com","telephone":"0513484859","clearance":1,"firstName":"Rebeka","lastName":"Rogahn","mail":"לא ידוע","tz":"337946990","personalNumber":"","rank":"mega","rld":null,"job":"Product Intranet Producer","profession":"Administrator","department":"city6","stype":"","hr":"Rebeka Rogahn","company":"לא ידוע","isPortalUser":false,"tags":[{"name":"transportable"}],"domains":["external","local"]},{"domUser":"e245905571@rafael.turtle.com","telephone":"0589387026","clearance":1,"firstName":"Victor","lastName":"Gorczany","mail":"","tz":null,"personalNumber":"לא ידוע","rank":"unknown","rld":null,"job":"Principal Solutions Specialist","profession":"","department":"city2","stype":"","hr":"quia/molestiae/quia/ex","company":"interstellar","isPortalUser":true,"tags":[{"name":"information"}],"domains":["local","external"]},{"domUser":"i677682039@turtle.com","telephone":"0515420182","clearance":5,"firstName":"Terrill","lastName":"Leffler","mail":null,"tz":"859706418","personalNumber":"322050996","rank":"mega","rld":"","job":"Dynamic Applications Developer","profession":"לא ידוע","department":"city1","stype":"","hr":"","company":"","isPortalUser":true,"tags":[{"name":"transportable"}],"domains":["local","external"]},{"domUser":"e273584520@rafael.turtle.com","telephone":"0599972615","clearance":4,"firstName":"Wilmer","lastName":"Corkery","mail":"לא ידוע","tz":"לא ידוע","personalNumber":"837188259","rank":"rookie","rld":null,"job":"Regional Assurance Orchestrator","profession":"Engineer","department":"city4","stype":"","hr":"nihil/at/eum/officia","company":"","isPortalUser":false,"tags":[{"name":"transportable"}],"domains":["local"]},{"domUser":"e770266894@turtle.com","telephone":"0504602148","clearance":4,"firstName":"Jermaine","lastName":"Doyle","mail":"","tz":null,"personalNumber":"לא ידוע","rank":"champion","rld":"","job":"Internal Operations Technician","profession":"Designer","department":"city1","stype":"","hr":"Jermaine Doyle","company":"","isPortalUser":false,"tags":[],"domains":["external","local"]},{"domUser":"e663324988@turtle.com","telephone":"0514735642","clearance":3,"firstName":"Raphaelle","lastName":"Howell","mail":"","tz":"302110929","personalNumber":"","rank":"champion","rld":"2020-03-20T08:03:48.910Z","job":"Human Infrastructure Officer","profession":"Consultant","department":"city3","stype":"","hr":"Raphaelle Howell","company":"","isPortalUser":false,"tags":[{"name":"transportable"},{"name":"information"}],"domains":["local","external"]},{"domUser":"e232719509@turtle.com","telephone":"0544114098","clearance":1,"firstName":"Patsy","lastName":"Cummerata","mail":"לא ידוע","tz":"לא ידוע","personalNumber":"","rank":"ultimate","rld":"לא ידוע","job":"Principal Configuration Producer","profession":"","department":"city4","stype":"","hr":null,"company":"","isPortalUser":false,"tags":[{"name":"transportable"}],"domains":["local","external"]},{"domUser":"e751349862@turtle.com","telephone":"0536231803","clearance":5,"firstName":"Godfrey","lastName":"Barrows","mail":null,"tz":"","personalNumber":"","rank":"mega","rld":null,"job":"International Functionality Representative","profession":"Analyst","department":"city4","stype":"","hr":null,"company":"odyssey","isPortalUser":true,"tags":[{"name":"information"},{"name":"transportable"}],"domains":["local"]},{"domUser":"e224666900@turtle.com","telephone":"0506816447","clearance":1,"firstName":"Antwan","lastName":"Kertzmann","mail":null,"tz":"508228376","personalNumber":"","rank":"unknown","rld":null,"job":"Dynamic Tactics Liaison","profession":"Supervisor","department":"city5","stype":"","hr":null,"company":"odyssey","isPortalUser":true,"tags":[{"name":"information"}],"domains":["local","external"]},{"domUser":"m698097139@turtle.com","telephone":"0529006480","clearance":5,"firstName":"Davon","lastName":"Jacobi","mail":"לא ידוע","tz":"807607536","personalNumber":"לא ידוע","rank":"mega","rld":"לא ידוע","job":"Regional Intranet Facilitator","profession":"לא ידוע","department":"city4","stype":"","hr":"distinctio/voluptatum/et/illo","company":"odyssey","isPortalUser":false,"tags":[{"name":"information"}],"domains":["external","local"]},{"domUser":"m292767451@donatelo.turtle.com","telephone":"0595732302","clearance":2,"firstName":"Mia","lastName":"Ullrich","mail":null,"tz":"871506259","personalNumber":"","rank":"unknown","rld":"לא ידוע","job":"Internal Applications Designer","profession":"","department":"city1","stype":"","hr":"Mia Ullrich","company":"interstellar","isPortalUser":false,"tags":[{"name":"transportable"},{"name":"transportable"}],"domains":["external","local"]},{"domUser":"m263888474@rafael.turtle.com","telephone":"0566933737","clearance":3,"firstName":"Jamal","lastName":"Prosacco","mail":null,"tz":"452211022","personalNumber":"","rank":"rookie","rld":"","job":"Central Brand Strategist","profession":"null","department":"city4","stype":"","hr":"","company":"odyssey","isPortalUser":false,"tags":[{"name":"information"},{"name":"information"}],"domains":["external","local"]},{"domUser":"m974616466@turtle.com","telephone":"0521661003","clearance":3,"firstName":"Maud","lastName":"Fritsch","mail":"","tz":"856536792","personalNumber":"","rank":"rookie","rld":null,"job":"Investor Research Facilitator","profession":"לא ידוע","department":"city1","stype":"","hr":null,"company":null,"isPortalUser":false,"tags":[{"name":"information"},{"name":"information"}],"domains":["local","external"]},{"domUser":"e347370190@donatelo.turtle.com","telephone":"0589774356","clearance":3,"firstName":"Maxine","lastName":"Schinner","mail":"","tz":"782013890","personalNumber":"27166298","rank":"mega","rld":null,"job":"Central Directives Officer","profession":"Associate","department":"city6","stype":"","hr":"Maxine Schinner","company":"odyssey","isPortalUser":true,"tags":[],"domains":["local","external"]},{"domUser":"e492670248@turtle.com","telephone":"0572797343","clearance":3,"firstName":"Noe","lastName":"Lubowitz","mail":"לא ידוע","tz":"","personalNumber":"","rank":"mega","rld":"","job":"Customer Functionality Officer","profession":"לא ידוע","department":"city4","stype":"","hr":"","company":"interstellar","isPortalUser":false,"tags":[{"name":"information"}],"domains":["local"]}]